lofigui/__init__.py
lofigui/app.py
lofigui/context.py
lofigui/controller.py
lofigui/favicon.py
lofigui/markdown.py
lofigui/options.py
lofigui/print.py
lofigui/static/README.md
lofigui/static/favicon.svg
lofigui-0.13.0.dist-info/METADATA
lofigui-0.13.0.dist-info/WHEEL
lofigui-0.13.0.dist-info/licenses/LICENSE
lofigui-0.13.0.dist-info/RECORD
