Metadata-Version: 2.4
Name: lofigui
Version: 0.13.0
Summary: Lofi GUI tooling
Author-email: Humphrey Drummond <hum3@drummond.info>
License: MIT
License-File: LICENSE
Requires-Python: >=3.9
Requires-Dist: jinja2>=3.1.2
Requires-Dist: markdown>=3.4.3
Provides-Extra: dev
Requires-Dist: black>=23.3.0; extra == 'dev'
Requires-Dist: flake8>=6.0.0; extra == 'dev'
Requires-Dist: mypy>=1.4.0; extra == 'dev'
Requires-Dist: pytest-asyncio>=0.21.0; extra == 'dev'
Requires-Dist: pytest-cov>=4.1.0; extra == 'dev'
Requires-Dist: pytest>=7.4.0; extra == 'dev'
Requires-Dist: types-markdown>=3.4.0; extra == 'dev'
Provides-Extra: examples
Requires-Dist: fastapi>=0.96.0; extra == 'examples'
Requires-Dist: httpx>=0.24.0; extra == 'examples'
Requires-Dist: pygal>=3.0.0; extra == 'examples'
Requires-Dist: uvicorn>=0.22.0; extra == 'examples'
